beebole/__init__.py
beebole/base.py
beebole/client.py
beebole/exceptions.py
beebole/interfaces/__init__.py
beebole/interfaces/entities/__init__.py
beebole/interfaces/entities/absence.py
beebole/interfaces/entities/company.py
beebole/interfaces/entities/custom_fields.py
beebole/interfaces/entities/group.py
beebole/interfaces/entities/jobs.py
beebole/interfaces/entities/person.py
beebole/interfaces/entities/project.py
beebole/interfaces/entities/subproject.py
beebole/interfaces/entities/task.py
beebole/interfaces/entities/time_entry.py
beebole/interfaces/responses/__init__.py
beebole/interfaces/responses/absence.py
beebole/interfaces/responses/custom_field.py
beebole/interfaces/responses/group.py
beebole/interfaces/responses/jobs.py
beebole/interfaces/responses/simple.py
beebole/services/__init__.py
beebole/services/absence.py
beebole/services/company.py
beebole/services/custom_field.py
beebole/services/group.py
beebole/services/person.py
beebole/services/project.py
beebole/services/subproject.py
beebole/services/task.py
beebole/services/time.py
beebole/utils.py
beebole-1.0.0.dist-info/LICENSE
beebole-1.0.0.dist-info/WHEEL
beebole-1.0.0.dist-info/METADATA
beebole-1.0.0.dist-info/RECORD
